{
    "Tournaments_Players": {
        "1": {
            "tournament_id": 1,
            "player_id": 1,
            "player_points": 0.0
        },
        "2": {
            "tournament_id": 1,
            "player_id": 2,
            "player_points": 0.5
        },
        "3": {
            "tournament_id": 1,
            "player_id": 3,
            "player_points": 0.0
        },
        "4": {
            "tournament_id": 1,
            "player_id": 4,
            "player_points": 2.0
        },
        "5": {
            "tournament_id": 1,
            "player_id": 5,
            "player_points": 1.0
        },
        "6": {
            "tournament_id": 1,
            "player_id": 6,
            "player_points": 0.5
        },
        "7": {
            "tournament_id": 1,
            "player_id": 7,
            "player_points": 0.0
        },
        "8": {
            "tournament_id": 1,
            "player_id": 8,
            "player_points": 1.0
        },
        "9": {
            "tournament_id": 2,
            "player_id": 1,
            "player_points": 0.0
        },
        "10": {
            "tournament_id": 2,
            "player_id": 2,
            "player_points": 0.0
        },
        "11": {
            "tournament_id": 2,
            "player_id": 3,
            "player_points": 1.0
        },
        "12": {
            "tournament_id": 2,
            "player_id": 4,
            "player_points": 0.5
        },
        "13": {
            "tournament_id": 2,
            "player_id": 5,
            "player_points": 1.0
        },
        "14": {
            "tournament_id": 2,
            "player_id": 6,
            "player_points": 0.0
        },
        "15": {
            "tournament_id": 2,
            "player_id": 7,
            "player_points": 1.0
        },
        "16": {
            "tournament_id": 2,
            "player_id": 8,
            "player_points": 0.5
        }
    }
}